{
    "project": "Mozilla", 
    "original_link": "http://dont.know.yet/392428", 
    "comments": [
        {
            "date": "2007-08-16 00:56:43", 
            "sentences": [
                {
                    "is_in_lex_summary": false, 
                    "text": "User-Agent:       Mozilla/5.0 (X11;", 
                    "is_in_email_summary": true
                }, 
                {
                    "is_in_lex_summary": false, 
                    "text": "U;", 
                    "is_in_email_summary": false
                }, 
                {
                    "is_in_lex_summary": false, 
                    "text": "Linux i686;", 
                    "is_in_email_summary": false
                }, 
                {
                    "is_in_lex_summary": false, 
                    "text": "en-US;", 
                    "is_in_email_summary": false
                }, 
                {
                    "is_in_lex_summary": false, 
                    "text": "rv:1.8.1.6)", 
                    "is_in_email_summary": false
                }, 
                {
                    "is_in_lex_summary": false, 
                    "text": "Gecko/20061201 Firefox/2.0.0.6 (Ubuntu-feisty)", 
                    "is_in_email_summary": false
                }, 
                {
                    "is_in_lex_summary": false, 
                    "text": "Build Identifier: Mozilla/5.0 (X11;", 
                    "is_in_email_summary": false
                }, 
                {
                    "is_in_lex_summary": false, 
                    "text": "U;", 
                    "is_in_email_summary": false
                }, 
                {
                    "is_in_lex_summary": false, 
                    "text": "Linux i686;", 
                    "is_in_email_summary": false
                }, 
                {
                    "is_in_lex_summary": false, 
                    "text": "en-US;", 
                    "is_in_email_summary": false
                }, 
                {
                    "is_in_lex_summary": false, 
                    "text": "rv:1.8.1.6)", 
                    "is_in_email_summary": false
                }, 
                {
                    "is_in_lex_summary": false, 
                    "text": "Gecko/20061201 Firefox/2.0.0.6 (Ubuntu-feisty)", 
                    "is_in_email_summary": false
                }, 
                {
                    "is_in_lex_summary": false, 
                    "text": "", 
                    "is_in_email_summary": false
                }, 
                {
                    "is_in_lex_summary": true, 
                    "text": "Link local IP addresses are specific to an interface, therefore it does not\nmake sense to specify a link-local address (eg fe80::21c:10ff:fe22:f9f) without\nan interface (eg eth0).", 
                    "is_in_email_summary": true
                }, 
                {
                    "is_in_lex_summary": false, 
                    "text": "", 
                    "is_in_email_summary": false
                }, 
                {
                    "is_in_lex_summary": false, 
                    "text": "", 
                    "is_in_email_summary": false
                }, 
                {
                    "is_in_lex_summary": true, 
                    "text": "The correct (at least I think the correct) format for specifying an interface\nin a URL is http://[<ipv6linklocal>%<interface>]/  eg", 
                    "is_in_email_summary": true
                }, 
                {
                    "is_in_lex_summary": true, 
                    "text": "http://[fe80::21c:10ff:fe22:f9f%eth0]", 
                    "is_in_email_summary": true
                }, 
                {
                    "is_in_lex_summary": false, 
                    "text": "", 
                    "is_in_email_summary": false
                }, 
                {
                    "is_in_lex_summary": false, 
                    "text": "", 
                    "is_in_email_summary": false
                }, 
                {
                    "is_in_lex_summary": false, 
                    "text": "", 
                    "is_in_email_summary": false
                }, 
                {
                    "is_in_lex_summary": false, 
                    "text": "Reproducible: Always", 
                    "is_in_email_summary": false
                }, 
                {
                    "is_in_lex_summary": false, 
                    "text": "", 
                    "is_in_email_summary": false
                }, 
                {
                    "is_in_lex_summary": false, 
                    "text": "Steps to Reproduce:", 
                    "is_in_email_summary": false
                }, 
                {
                    "is_in_lex_summary": true, 
                    "text": "1. Type in the URL above and press enter", 
                    "is_in_email_summary": false
                }, 
                {
                    "is_in_lex_summary": false, 
                    "text": "2. ????", 
                    "is_in_email_summary": false
                }, 
                {
                    "is_in_lex_summary": false, 
                    "text": "3. Profit!", 
                    "is_in_email_summary": false
                }, 
                {
                    "is_in_lex_summary": false, 
                    "text": "Actual Results:", 
                    "is_in_email_summary": false
                }, 
                {
                    "is_in_lex_summary": false, 
                    "text": "Firefox says", 
                    "is_in_email_summary": false
                }, 
                {
                    "is_in_lex_summary": true, 
                    "text": "http://[www.fe80::21c:10ff:fe22:f9f%eth0.com]/ is an invalid address (which of\ncourse it is)", 
                    "is_in_email_summary": true
                }, 
                {
                    "is_in_lex_summary": false, 
                    "text": "", 
                    "is_in_email_summary": false
                }, 
                {
                    "is_in_lex_summary": false, 
                    "text": "Expected Results:", 
                    "is_in_email_summary": false
                }
            ], 
            "name": "Nick 'Zaf' Clifford", 
            "email": "Nick 'Zaf' Clifford"
        }, 
        {
            "date": "2007-08-16 05:35:13", 
            "sentences": [
                {
                    "is_in_lex_summary": true, 
                    "text": "The best explanation I found is", 
                    "is_in_email_summary": false
                }, 
                {
                    "is_in_lex_summary": false, 
                    "text": "<http://lists.macosforge.org/pipermail/webkit-unassigned/2006-December/024077.html>\n.", 
                    "is_in_email_summary": false
                }, 
                {
                    "is_in_lex_summary": true, 
                    "text": "The problem is that there's no official syntax definition that allows an\ninterface identifier in an IPv6 address.", 
                    "is_in_email_summary": true
                }, 
                {
                    "is_in_lex_summary": false, 
                    "text": "", 
                    "is_in_email_summary": false
                }, 
                {
                    "is_in_lex_summary": true, 
                    "text": "Reported before in bug 292307, but that's now expired.", 
                    "is_in_email_summary": false
                }
            ], 
            "name": "Jo Hermans", 
            "email": "Jo Hermans"
        }, 
        {
            "date": "2007-08-16 08:20:46", 
            "sentences": [
                {
                    "is_in_lex_summary": true, 
                    "text": "Note that Webkit (= Safari) has resolved this bug as invalid, because there's\nno spec that says that interface-identifiers have to be supported.", 
                    "is_in_email_summary": true
                }, 
                {
                    "is_in_lex_summary": true, 
                    "text": "And they\nwould be of no use on the Internet either, since such an URL would probably\nonly work from your computer .", 
                    "is_in_email_summary": true
                }, 
                {
                    "is_in_lex_summary": false, 
                    "text": "", 
                    "is_in_email_summary": false
                }, 
                {
                    "is_in_lex_summary": false, 
                    "text": "http://bugs.webkit.org/show_bug.cgi?", 
                    "is_in_email_summary": false
                }, 
                {
                    "is_in_lex_summary": false, 
                    "text": "id=11773", 
                    "is_in_email_summary": false
                }, 
                {
                    "is_in_lex_summary": false, 
                    "text": "", 
                    "is_in_email_summary": false
                }, 
                {
                    "is_in_lex_summary": true, 
                    "text": "Leaving this bug open until someone decides if this is worth fixing or not.", 
                    "is_in_email_summary": false
                }, 
                {
                    "is_in_lex_summary": true, 
                    "text": "My\nvote is for rejecting it.", 
                    "is_in_email_summary": false
                }
            ], 
            "name": "Jo Hermans", 
            "email": "Jo Hermans"
        }, 
        {
            "date": "2007-08-16 13:16:27", 
            "sentences": [
                {
                    "is_in_lex_summary": false, 
                    "text": "> And they would be of no use on the Internet either,", 
                    "is_in_email_summary": false
                }, 
                {
                    "is_in_lex_summary": false, 
                    "text": "> since such an URL would probably only work from your", 
                    "is_in_email_summary": false
                }, 
                {
                    "is_in_lex_summary": false, 
                    "text": "> computer .", 
                    "is_in_email_summary": false
                }, 
                {
                    "is_in_lex_summary": false, 
                    "text": "", 
                    "is_in_email_summary": false
                }, 
                {
                    "is_in_lex_summary": true, 
                    "text": "I'm going to disagree with you on that.", 
                    "is_in_email_summary": false
                }, 
                {
                    "is_in_lex_summary": true, 
                    "text": "Whilst the URLs wouldn't be of any use\non the big wide world Internet, on a local area network, they can be very\nuseful.", 
                    "is_in_email_summary": true
                }, 
                {
                    "is_in_lex_summary": true, 
                    "text": "Case in point was a network device I plugged into my local network, it\ncame up without a valid IPv4 IP address (it had its own DHCP server and thought\nit knew best), traditionally you'd have to change your own IP address (or add\nan alias) to your PC, login to the device, change it back to a sane address,\netc, etc.", 
                    "is_in_email_summary": true
                }, 
                {
                    "is_in_lex_summary": false, 
                    "text": "", 
                    "is_in_email_summary": false
                }, 
                {
                    "is_in_lex_summary": true, 
                    "text": "With v6, I found the device by doing an all nodes ping, got its v6 link-local\naddress, and tried (and failed) to login to it with Firefox.", 
                    "is_in_email_summary": true
                }, 
                {
                    "is_in_lex_summary": true, 
                    "text": "I resorted to\nusing the telnet interface to change its IPv4 address and configure it that\nway.", 
                    "is_in_email_summary": false
                }, 
                {
                    "is_in_lex_summary": true, 
                    "text": "I could have also got its global scoped address and changed it with that\ntoo I guess.", 
                    "is_in_email_summary": false
                }, 
                {
                    "is_in_lex_summary": false, 
                    "text": "", 
                    "is_in_email_summary": false
                }, 
                {
                    "is_in_lex_summary": true, 
                    "text": "As for there being no standard, I fail to see how that should stop a feature\nbeing implemented.", 
                    "is_in_email_summary": false
                }, 
                {
                    "is_in_lex_summary": false, 
                    "text": "The commonly accepted format is", 
                    "is_in_email_summary": false
                }, 
                {
                    "is_in_lex_summary": false, 
                    "text": "<ipv6-link-local>%<interface>.", 
                    "is_in_email_summary": false
                }
            ], 
            "name": "Nick 'Zaf' Clifford", 
            "email": "Nick 'Zaf' Clifford"
        }, 
        {
            "date": "2007-08-20 17:50:43", 
            "sentences": [
                {
                    "is_in_lex_summary": true, 
                    "text": "So you tested this with Firefox 2.0.0.6 on Ubuntu?", 
                    "is_in_email_summary": false
                }, 
                {
                    "is_in_lex_summary": true, 
                    "text": "Could you make a log per the\ninstructions at http://www.mozilla.org/projects/netlib/http/http-debugging.html\nand attach it to this bug?", 
                    "is_in_email_summary": true
                }
            ], 
            "name": "Christian :Biesinger (don't email me, ping me on IRC)", 
            "email": "Christian :Biesinger (don't email me, ping me on IRC)"
        }, 
        {
            "date": "2007-08-20 18:11:17", 
            "sentences": [
                {
                    "is_in_lex_summary": false, 
                    "text": "Yes.", 
                    "is_in_email_summary": false
                }, 
                {
                    "is_in_lex_summary": false, 
                    "text": "Ubuntu Feisty", 
                    "is_in_email_summary": false
                }, 
                {
                    "is_in_lex_summary": true, 
                    "text": "Firefox 2.0.0.6", 
                    "is_in_email_summary": false
                }, 
                {
                    "is_in_lex_summary": false, 
                    "text": "x86 processor", 
                    "is_in_email_summary": false
                }, 
                {
                    "is_in_lex_summary": false, 
                    "text": "", 
                    "is_in_email_summary": false
                }, 
                {
                    "is_in_lex_summary": true, 
                    "text": "I have followed the http debugging instructions, and I will attach the debug\nlog (link-local-debug.txt), I have pruned only a few lines relating to cookies\nthat were sent on opening to various RSS feeds.", 
                    "is_in_email_summary": true
                }, 
                {
                    "is_in_lex_summary": false, 
                    "text": "", 
                    "is_in_email_summary": false
                }, 
                {
                    "is_in_lex_summary": true, 
                    "text": "Quick tip: to find the related lines to the problem, search for \"fe80\"", 
                    "is_in_email_summary": false
                }, 
                {
                    "is_in_lex_summary": false, 
                    "text": "I tried various different input methods, but none worked.", 
                    "is_in_email_summary": false
                }, 
                {
                    "is_in_lex_summary": true, 
                    "text": "The host in question was: fe80::208:a1ff:fe96:b473 on my eth0 interface.", 
                    "is_in_email_summary": false
                }, 
                {
                    "is_in_lex_summary": false, 
                    "text": "eg:", 
                    "is_in_email_summary": false
                }, 
                {
                    "is_in_lex_summary": false, 
                    "text": "$ telnet fe80::208:a1ff:fe96:b473%eth0 80", 
                    "is_in_email_summary": false
                }, 
                {
                    "is_in_lex_summary": false, 
                    "text": "Trying fe80::208:a1ff:fe96:b473%eth0...", 
                    "is_in_email_summary": false
                }, 
                {
                    "is_in_lex_summary": false, 
                    "text": "Connected to fe80::208:a1ff:fe96:b473%eth0.", 
                    "is_in_email_summary": false
                }, 
                {
                    "is_in_lex_summary": false, 
                    "text": "Escape character is '^]'.", 
                    "is_in_email_summary": false
                }, 
                {
                    "is_in_lex_summary": false, 
                    "text": "^]", 
                    "is_in_email_summary": false
                }, 
                {
                    "is_in_lex_summary": false, 
                    "text": "telnet> quit", 
                    "is_in_email_summary": false
                }
            ], 
            "name": "Nick 'Zaf' Clifford", 
            "email": "Nick 'Zaf' Clifford"
        }, 
        {
            "date": "2007-08-20 18:15:30", 
            "sentences": [
                {
                    "is_in_lex_summary": true, 
                    "text": "Created an attachment (id=277474) [details]", 
                    "is_in_email_summary": false
                }, 
                {
                    "is_in_lex_summary": true, 
                    "text": "Debug log using link-local address", 
                    "is_in_email_summary": false
                }, 
                {
                    "is_in_lex_summary": false, 
                    "text": "", 
                    "is_in_email_summary": false
                }, 
                {
                    "is_in_lex_summary": true, 
                    "text": "Debug log was too large to attach without modification.", 
                    "is_in_email_summary": false
                }, 
                {
                    "is_in_lex_summary": true, 
                    "text": "so instead I have\ntrimmed the debug log and only included the traffic related to the attempt to\nuse the fe80: address.", 
                    "is_in_email_summary": false
                }, 
                {
                    "is_in_lex_summary": true, 
                    "text": "I found this by searching for fe80, noting the timestamp, and trimming\neverything before that timestamp.", 
                    "is_in_email_summary": false
                }, 
                {
                    "is_in_lex_summary": true, 
                    "text": "If you need the rest of the log, let me know, and I'll put it up somewhere.", 
                    "is_in_email_summary": false
                }
            ], 
            "name": "Nick 'Zaf' Clifford", 
            "email": "Nick 'Zaf' Clifford"
        }, 
        {
            "date": "2007-08-20 20:40:43", 
            "sentences": [
                {
                    "is_in_lex_summary": true, 
                    "text": "Created an attachment (id=277483) [details]", 
                    "is_in_email_summary": false
                }, 
                {
                    "is_in_lex_summary": false, 
                    "text": "patch", 
                    "is_in_email_summary": false
                }, 
                {
                    "is_in_lex_summary": false, 
                    "text": "", 
                    "is_in_email_summary": false
                }, 
                {
                    "is_in_lex_summary": true, 
                    "text": "Found the problem.", 
                    "is_in_email_summary": false
                }, 
                {
                    "is_in_lex_summary": true, 
                    "text": "We consider all hostnames (this includes IP addresses)", 
                    "is_in_email_summary": false
                }, 
                {
                    "is_in_lex_summary": false, 
                    "text": "containing a percent sign as invalid.", 
                    "is_in_email_summary": false
                }, 
                {
                    "is_in_lex_summary": false, 
                    "text": "", 
                    "is_in_email_summary": false
                }, 
                {
                    "is_in_lex_summary": true, 
                    "text": "This patch makes it so that we always consider IP addresses valid.", 
                    "is_in_email_summary": false
                }
            ], 
            "name": "Christian :Biesinger (don't email me, ping me on IRC)", 
            "email": "Christian :Biesinger (don't email me, ping me on IRC)"
        }, 
        {
            "date": "2007-08-20 21:10:23", 
            "sentences": [
                {
                    "is_in_lex_summary": true, 
                    "text": "(From update of attachment 277483 [details])", 
                    "is_in_email_summary": false
                }, 
                {
                    "is_in_lex_summary": false, 
                    "text": "Makes sense.", 
                    "is_in_email_summary": false
                }, 
                {
                    "is_in_lex_summary": false, 
                    "text": "r+sr+a=bzbarsky", 
                    "is_in_email_summary": false
                }
            ], 
            "name": "Boris Zbarsky (:bz)", 
            "email": "Boris Zbarsky (:bz)"
        }, 
        {
            "date": "2007-08-21 10:14:58", 
            "sentences": [
                {
                    "is_in_lex_summary": false, 
                    "text": "Checking in nsURLHelper.cpp;", 
                    "is_in_email_summary": false
                }, 
                {
                    "is_in_lex_summary": false, 
                    "text": "/cvsroot/mozilla/netwerk/base/src/nsURLHelper.cpp,v  <--  nsURLHelper.cpp\nnew revision: 1.68;", 
                    "is_in_email_summary": false
                }, 
                {
                    "is_in_lex_summary": false, 
                    "text": "previous revision: 1.67", 
                    "is_in_email_summary": false
                }, 
                {
                    "is_in_lex_summary": false, 
                    "text": "done", 
                    "is_in_email_summary": false
                }
            ], 
            "name": "Christian :Biesinger (don't email me, ping me on IRC)", 
            "email": "Christian :Biesinger (don't email me, ping me on IRC)"
        }, 
        {
            "date": "2007-08-21 10:20:44", 
            "sentences": [
                {
                    "is_in_lex_summary": true, 
                    "text": "(From update of attachment 277483 [details])", 
                    "is_in_email_summary": false
                }, 
                {
                    "is_in_lex_summary": true, 
                    "text": "this just makes us always treat IP addresses as valid hostnames, should be low\nrisk.", 
                    "is_in_email_summary": true
                }
            ], 
            "name": "Christian :Biesinger (don't email me, ping me on IRC)", 
            "email": "Christian :Biesinger (don't email me, ping me on IRC)"
        }, 
        {
            "date": "2007-08-21 13:11:34", 
            "sentences": [
                {
                    "is_in_lex_summary": true, 
                    "text": "Just an FYI - I tried recompiling Firefox with the above patch, and from what I\ncan tell, it didn't work.", 
                    "is_in_email_summary": true
                }, 
                {
                    "is_in_lex_summary": true, 
                    "text": "That said, I'll happily confess that it was my first\ntime compiling Firefox, and I'm not 100% that the package I compiled is the one\nI'm running.", 
                    "is_in_email_summary": true
                }, 
                {
                    "is_in_lex_summary": false, 
                    "text": "", 
                    "is_in_email_summary": false
                }, 
                {
                    "is_in_lex_summary": false, 
                    "text": "", 
                    "is_in_email_summary": false
                }, 
                {
                    "is_in_lex_summary": true, 
                    "text": "So if you're 100% sure that the patch has fixed it, fine, but if you are\nworking on the assumption that the patch has fixed the problem, then maybe\nhold-fire before closing this report, until I can recompile the entire package\nagain, this time ensuring that I'm running the patched version.", 
                    "is_in_email_summary": true
                }
            ], 
            "name": "Nick 'Zaf' Clifford", 
            "email": "Nick 'Zaf' Clifford"
        }, 
        {
            "date": "2007-08-21 13:32:50", 
            "sentences": [
                {
                    "is_in_lex_summary": true, 
                    "text": "Well, I did test the patch and it worked for me.", 
                    "is_in_email_summary": false
                }, 
                {
                    "is_in_lex_summary": true, 
                    "text": "If it's not fixed for you\nthough, there may be an additional problem.", 
                    "is_in_email_summary": false
                }, 
                {
                    "is_in_lex_summary": true, 
                    "text": "You could wait until tomorrow and\ntry a nightly build:", 
                    "is_in_email_summary": false
                }, 
                {
                    "is_in_lex_summary": false, 
                    "text": "http://ftp.mozilla.org/pub/mozilla.org/firefox/nightly/latest-trunk/firefox-3.0a8pre.en-US.linux-i686.tar.bz2", 
                    "is_in_email_summary": false
                }, 
                {
                    "is_in_lex_summary": true, 
                    "text": "(what's currently there doesn't have the patch yet, so wait 24h or so)", 
                    "is_in_email_summary": false
                }
            ], 
            "name": "Christian :Biesinger (don't email me, ping me on IRC)", 
            "email": "Christian :Biesinger (don't email me, ping me on IRC)"
        }, 
        {
            "date": "2007-08-26 22:56:40", 
            "sentences": [
                {
                    "is_in_lex_summary": true, 
                    "text": "Nick, did you get a chance to test this in a nightly build yet?", 
                    "is_in_email_summary": true
                }
            ], 
            "name": "Christian :Biesinger (don't email me, ping me on IRC)", 
            "email": "Christian :Biesinger (don't email me, ping me on IRC)"
        }, 
        {
            "date": "2007-09-07 11:41:48", 
            "sentences": [
                {
                    "is_in_lex_summary": true, 
                    "text": "(From update of attachment 277483 [details])", 
                    "is_in_email_summary": false
                }, 
                {
                    "is_in_lex_summary": true, 
                    "text": "not approved for 1.8 branch (no trunk verification, nervous about any security\nimplications of relaxing the '%' check for all hostnames)", 
                    "is_in_email_summary": true
                }
            ], 
            "name": "Daniel Veditz", 
            "email": "Daniel Veditz"
        }, 
        {
            "date": "2008-02-12 07:21:01", 
            "sentences": [
                {
                    "is_in_lex_summary": true, 
                    "text": "It's not relaxing the % check, it's just saying that if it fails to parse as a\nhostname, but parses as an IP(4/6) address, then it's okay.", 
                    "is_in_email_summary": true
                }
            ], 
            "name": "Norman Rasmussen", 
            "email": "Norman Rasmussen"
        }
    ], 
    "title": "Firefox does not appear to support IPv6 link-local addresses"
}